<?xml version="1.0" encoding="utf-8"?><ArrayOfQuestionAndAnswer xmlns:xsi="http://www.w3.org/2001/XMLSchema-instance" xmlns:xsd="http://www.w3.org/2001/XMLSchema"><QuestionAndAnswer><question>Who is Poopio?</question><Answers><Answer><answerString>A a goofy goober</answerString><isCorrect>true</isCorrect></Answer><Answer><answerString>B a dog</answerString><isCorrect>false</isCorrect></Answer><Answer><answerString>C a Manimal</answerString><isCorrect>false</isCorrect></Answer><Answer><answerString>D my son</answerString><isCorrect>true</isCorrect></Answer></Answers></QuestionAndAnswer><QuestionAndAnswer><question>Who is Mr Bear?</question><Answers><Answer><answerString>A My special boy</answerString><isCorrect>true</isCorrect></Answer><Answer><answerString>B a duck</answerString><isCorrect>false</isCorrect></Answer><Answer><answerString>C a dog</answerString><isCorrect>false</isCorrect></Answer><Answer><answerString>D a horse</answerString><isCorrect>false</isCorrect></Answer></Answers></QuestionAndAnswer></ArrayOfQuestionAndAnswer>